git_acquire/__init__.py
git_acquire/__main__.py
git_acquire/acquire.py
git_acquire-0.1.0.dist-info/Apache-2.0.txt
git_acquire-0.1.0.dist-info/CC-BY-4.0.txt
git_acquire-0.1.0.dist-info/CC0-1.0.txt
git_acquire-0.1.0.dist-info/METADATA
git_acquire-0.1.0.dist-info/WHEEL
git_acquire-0.1.0.dist-info/entry_points.txt
git_acquire-0.1.0.dist-info/top_level.txt
git_acquire-0.1.0.dist-info/RECORD
